<?xml version="1.0" encoding="UTF-8"?>
<DCOPData Time="Thu May 8 12:59:29 2025" Simulator="hpeesofsim" Version="1.0">
 <Controller name="SP1">
  <SweepCondition>
   <P>freq: 1.0000000000000000e+07</P>
  </SweepCondition>
  <DC_OPDeclaration/>
  <DC_Voltages>
   <V>0: 0.0000000000000000e+00</V>
   <V>AVX_600S_C2.P1: 1.5380882294660110e-08</V>
   <V>AVX_600S_C2.P2: 8.8835383534271195e-01</V>
   <V>AVX_600S_C4.P1: 7.6889288184723017e-15</V>
   <V>AVX_600S_C4.P2: 1.5377773056221048e-08</V>
   <V>AVX_600S_C7.P1: 2.6947076816576220e-06</V>
   <V>AVX_600S_C7.P2: 1.6196070458890291e-15</V>
   <V>AVX_600S_C8.P1: 2.9019742078694062e+00</V>
   <V>AVX_600S_C8.P2: 2.6947149368887292e-06</V>
   <V>CLC_0402CS1._net1868: 1.5373775375334239e-08</V>
   <V>CLC_0402CS1._net1869: 6.1856318431206695e-11</V>
   <V>CLC_0402CS3._net1868: 1.5953686054016578e-15</V>
   <V>CLC_0402CS3._net1869: 1.8740937541775807e-16</V>
   <V>CLC_0603HL_L1.P1: 9.0689821696480510e-01</V>
   <V>CLC_0603HL_L1.P2: 8.8835564866976013e-01</V>
   <V>CLC_0603HL_L2.P1: 8.8835208192780368e-01</V>
   <V>CLC_0603HL_L2.P2: 8.7042207778789804e-01</V>
   <V>CLC_0603HL_L5.P1: 2.9627680289533251e+00</V>
   <V>CLC_0603HL_L5.P2: 2.9019801524715989e+00</V>
   <V>INF_BFP420_1.L6._net21: 8.8835357686494754e-01</V>
   <V>INF_BFP420_1.L6.pin1: 8.8835367283723710e-01</V>
   <V>INF_BFP420_1.L6.pin2: 8.8835357686494754e-01</V>
   <V>INF_BFP420_1.L7._net21: 5.7810967058963389e-05</V>
   <V>INF_BFP420_1.L7.pin1: 4.6913225245292114e-05</V>
   <V>INF_BFP420_1.L7.pin2: 5.7810967058963389e-05</V>
   <V>INF_BFP420_1._net42: 4.3785226760869056e-05</V>
   <V>INF_BFP420_1._net43: 4.3785226760869056e-05</V>
   <V>INF_BFP420_1._net44: 4.6913225245292114e-05</V>
   <V>INF_BFP420_1._net45: 4.6913225245292114e-05</V>
   <V>INF_BFP420_1._net47: 8.8835367283723710e-01</V>
   <V>INF_BFP420_1._net48: 8.8835367283723710e-01</V>
   <V>INF_BFP420_1._net52: 2.9019620697070496e+00</V>
   <V>INF_BFP420_1._net53: 2.9019682632947816e+00</V>
   <V>INF_BFP420_1._net74: 5.7810967058963389e-05</V>
   <V>INF_BFP420_1._net75: 8.8835357686494754e-01</V>
   <V>INF_BFP420_1._net76: 2.9019620697070496e+00</V>
   <V>INF_BFP420_1._net86: 8.8835374869043038e-01</V>
   <V>INF_BFP420_1._net87: 8.8835373524647376e-01</V>
   <V>KOA_RK73B2A_R2._net50: 8.7042012954899861e-01</V>
   <V>KOA_RK73B2A_R2._net51: 2.6351458907283179e-05</V>
   <V>KOA_RK73B2A_R3._net50: 9.0690023176371748e-01</V>
   <V>KOA_RK73B2A_R3._net51: 2.9999930666726993e+00</V>
   <V>KOA_RK73B2A_R4._net50: 2.9627746340441341e+00</V>
   <V>KOA_RK73B2A_R4._net51: 2.9999910664978469e+00</V>
   <V>KOA_RK73B2A_R5._net50: 2.6946946225198698e-06</V>
   <V>KOA_RK73B2A_R5._net51: 2.0206488267880252e-10</V>
   <V>N__0: 1.5380882294660110e-08</V>
   <V>N__1: 1.5379105587020188e-08</V>
   <V>N__10: 7.6888980629415688e-15</V>
   <V>N__11: 1.8755474839056857e-10</V>
   <V>N__12: 1.9335868602710942e-10</V>
   <V>N__13: 2.5961779956335460e-05</V>
   <V>N__14: 2.5182499982437407e-05</V>
   <V>N__15: 8.7042129850792394e-01</V>
   <V>N__16: 8.7042207778789804e-01</V>
   <V>N__17: 4.3785226760869056e-05</V>
   <V>N__18: 4.3118010201981752e-05</V>
   <V>N__19: 8.8835381538043723e-01</V>
   <V>N__2: 1.5373775375334239e-08</V>
   <V>N__20: 8.8835208192780368e-01</V>
   <V>N__21: 4.3118010201981752e-05</V>
   <V>N__22: 8.8835380206825798e-01</V>
   <V>N__23: 8.8835383534271195e-01</V>
   <V>N__24: 8.8835383534448853e-01</V>
   <V>N__25: 8.8835383534537671e-01</V>
   <V>N__26: 8.8835286120777768e-01</V>
   <V>N__27: 6.0079610822040327e-11</V>
   <V>N__28: 1.5377773056267175e-08</V>
   <V>N__29: 2.6947033287165221e-06</V>
   <V>N__3: 1.5375552082943406e-08</V>
   <V>N__30: 2.9019682632947816e+00</V>
   <V>N__31: 2.9019709052724614e+00</V>
   <V>N__32: 8.8835564866976013e-01</V>
   <V>N__33: 1.8740937541775807e-16</V>
   <V>N__34: 2.6947076816630117e-06</V>
   <V>N__35: 2.9019722263934007e+00</V>
   <V>N__36: 2.6946946225198698e-06</V>
   <V>N__37: 2.6947004264575065e-06</V>
   <V>N__38: 2.9999930666726993e+00</V>
   <V>N__39: 2.9627746340441341e+00</V>
   <V>N__4: 8.8835484276631316e-01</V>
   <V>N__40: 3.0000000000000000e+00</V>
   <V>N__41: 9.0690023176371748e-01</V>
   <V>N__42: 2.9999938725761464e+00</V>
   <V>N__43: 8.8835378862430570e-01</V>
   <V>N__44: 2.9999950855413591e+00</V>
   <V>N__45: 2.9627719920606501e+00</V>
   <V>N__46: 4.3785226760869056e-05</V>
   <V>N__47: 2.9999910664978469e+00</V>
   <V>N__48: 5.7414460572910315e-11</V>
   <V>N__49: 1.5377773056251800e-08</V>
   <V>N__5: 1.5377773056221048e-08</V>
   <V>N__50: 6.1856318431206695e-11</V>
   <V>N__51: 8.8835374869043038e-01</V>
   <V>N__52: 2.6947076816576220e-06</V>
   <V>N__53: 1.6074725541738374e-15</V>
   <V>N__54: 1.5376440525583374e-08</V>
   <V>N__55: 2.6947076816657074e-06</V>
   <V>N__56: 1.7395164259384972e-16</V>
   <V>N__57: 1.7933462806370371e-16</V>
   <V>N__58: 1.5953686054016578e-15</V>
   <V>N__59: 2.9999982758841410e+00</V>
   <V>N__6: 7.6889288184723017e-15</V>
   <V>N__60: 8.7042090882897272e-01</V>
   <V>N__61: 8.8835443977429429e-01</V>
   <V>N__62: 1.6074757694404405e-15</V>
   <V>N__64: 2.6351458907283179e-05</V>
   <V>N__65: 7.6888826836384260e-15</V>
   <V>N__66: 8.7042012954899861e-01</V>
   <V>N__67: 8.8835377531212645e-01</V>
   <V>N__68: 2.9999946825493398e+00</V>
   <V>N__69: 2.9999942755681648e+00</V>
   <V>N__70: 1.6115226533781557e-15</V>
   <V>N__71: 1.8202638994790412e-16</V>
   <V>N__72: 5.9191168182076690e-11</V>
   <V>N__73: 1.9626094504226164e-10</V>
   <V>N__74: 1.6196070458890291e-15</V>
   <V>N__75: 1.6142176305289585e-15</V>
   <V>N__76: 1.6007515908715120e-15</V>
   <V>N__77: 9.0689942586027050e-01</V>
   <V>N__78: 2.9019742078694062e+00</V>
   <V>N__79: 9.0689821696480510e-01</V>
   <V>N__8: 8.8835325088672867e-01</V>
   <V>N__80: 9.0689902286825197e-01</V>
   <V>N__82: 2.9627680289533251e+00</V>
   <V>N__83: 2.9019761893642744e+00</V>
   <V>N__84: 2.9627706709368096e+00</V>
   <V>N__85: 2.9019775104881145e+00</V>
   <V>N__86: 1.6034433527557127e-15</V>
   <V>N__87: 2.9019742078723088e+00</V>
   <V>N__88: 2.0206488267880252e-10</V>
   <V>N__89: 2.9999937084813308e+00</V>
   <V>N__9: 2.6947149368887292e-06</V>
   <V>N__90: 2.9019801524715989e+00</V>
   <V>N__91: 0.0000000000000000e+00</V>
   <V>N__92: 0.0000000000000000e+00</V>
   <V>N__94: 2.6947120346270183e-06</V>
   <V>SNP1.p0: 0.0000000000000000e+00</V>
   <V>SNP1.p1: 0.0000000000000000e+00</V>
   <V>SNP1.p2: 0.0000000000000000e+00</V>
   <GV>0: 0.0000000000000000e+00</GV>
  </DC_Voltages>
  <DC_PinCurrents>
   <I>AVX_600S_C2: -8.8835381996094123e-09, 8.8835381996094123e-09</I>
   <I>AVX_600S_C4: -1.5377765367276853e-16, 1.5377765367276853e-16</I>
   <I>AVX_600S_C7: 2.6947076800353199e-14, -2.6947076800353199e-14</I>
   <I>AVX_600S_C8: 2.9019715131515672e-08, -2.9019715131515672e-08</I>
   <I>CLC_0402CS1: 8.8835380458317603e-09, -8.8835380458317603e-09</I>
   <I>CLC_0402CS3: 2.6914927349269723e-14, -2.6914927349269723e-14</I>
   <I>CLC_0603HL_L1: 4.0295172338541962e-03, -4.0295172338541962e-03</I>
   <I>CLC_0603HL_L2: 3.8963998694902247e-03, -3.8963998694902247e-03</I>
   <I>CLC_0603HL_L5: 1.3209917417856931e-02, -1.3209917417856931e-02</I>
   <I>Corn1: 4.0295172329933848e-03, -4.0295172329933848e-03</I>
   <I>Corn3: 1.3310847862157971e-04, -1.3310847862157971e-04</I>
   <I>Cros1: -8.8830347522161901e-09, 4.0295172339028795e-03, -1.3310848044056911e-04, -3.8963998695180635e-03</I>
   <I>INF_BFP420_1: 1.3310848044056911e-04, -6.6714984390290610e-03, 1.3209888398705516e-02, -6.6714984390290610e-03</I>
   <I>KOA_RK73B2A_R2: 3.8963998694902407e-03, -3.8963998694902407e-03</I>
   <I>KOA_RK73B2A_R3: -4.0295172338542058e-03, 4.0295172338542058e-03</I>
   <I>KOA_RK73B2A_R4: -1.3209917417857042e-02, 1.3209917417857042e-02</I>
   <I>KOA_RK73B2A_R5: 2.9019688182704151e-08, -2.9019688182704151e-08</I>
   <I>SNP1: 0.0000000000000000e+00, 0.0000000000000000e+00, 0.0000000000000000e+00</I>
   <I>SRC1: -1.7239434651711193e-02, 1.7239434651711193e-02</I>
   <I>Step1: -1.5377765367528830e-16, 1.5377765367528830e-16</I>
   <I>Step11: 3.8963998695180635e-03, -3.8963998695180635e-03</I>
   <I>Step12: 3.8963998694902524e-03, -3.8963998694902524e-03</I>
   <I>Step13: 4.0295172339028795e-03, -4.0295172339028795e-03</I>
   <I>Step14: 4.0295172329933848e-03, -4.0295172329933848e-03</I>
   <I>Step15: 1.3209917417043471e-02, -1.3209917417043471e-02</I>
   <I>Step18: 2.9019688182704171e-08, -2.9019688182704171e-08</I>
   <I>Step2: -1.5376697311275667e-16, 1.5376697311275667e-16</I>
   <I>Step20: 2.6914927349269629e-14, -2.6914927349269629e-14</I>
   <I>Step21: 2.6914927349269730e-14, -2.6914927349269730e-14</I>
   <I>Step23: 8.8835380458317686e-09, -8.8835380458317686e-09</I>
   <I>Step24: 2.6947076800352069e-14, -2.6947076800352069e-14</I>
   <I>Step25: 4.0295172339028795e-03, -4.0295172339028795e-03</I>
   <I>Step26: 3.8963998695180635e-03, -3.8963998695180635e-03</I>
   <I>Step27: 2.9019688180254022e-08, -2.9019688180254022e-08</I>
   <I>Step28: 8.8835380458318215e-09, -8.8835380458318215e-09</I>
   <I>Step29: 1.3209917417043471e-02, -1.3209917417043471e-02</I>
   <I>Step3: 8.8835380458306568e-09, -8.8835380458306568e-09</I>
   <I>Step30: 2.6947194475823721e-14, -2.6947194475823721e-14</I>
   <I>Step31: 1.3310847953107441e-04, -1.3310847953107441e-04</I>
   <I>Step32: 1.3209917418862460e-02, -1.3209917418862460e-02</I>
   <I>Step34: 2.6914927349269629e-14, -2.6914927349269629e-14</I>
   <I>Step35: 2.9019688182704276e-08, -2.9019688182704276e-08</I>
   <I>Step36: 1.3209917418862460e-02, -1.3209917418862460e-02</I>
   <I>Step4: -8.8835381996247350e-09, 8.8835381996247350e-09</I>
   <I>Step5: -8.8839442469179630e-09, 8.8839442469179630e-09</I>
   <I>Step6: 4.0295172348123742e-03, -4.0295172348123742e-03</I>
   <I>Step7: 1.3209888396886527e-02, -1.3209888396886527e-02</I>
   <I>Step8: 3.8963998686085688e-03, -3.8963998686085688e-03</I>
   <I>TL1: -1.5377765368175065e-16, 1.5377765368175065e-16</I>
   <I>TL10: 2.6947194475823721e-14, -2.6947194475823721e-14</I>
   <I>TL13: 4.0295172366313636e-03, -4.0295172366313636e-03</I>
   <I>TL14: -4.0295172366313636e-03, 4.0295172366313636e-03</I>
   <I>TL16: 1.3310847862157971e-04, -1.3310847862157971e-04</I>
   <I>TL17: 2.9020156944170594e-08, -2.9020156944170594e-08</I>
   <I>TL2: -8.8821252575144172e-09, 8.8821252575144172e-09</I>
   <I>TL20: 1.3209888398705516e-02, -1.3209888398705516e-02</I>
   <I>TL21: -2.6947076800350454e-14, 2.6947076800350454e-14</I>
   <I>TL23: -1.7239434651855845e-02, 1.7239434651855845e-02</I>
   <I>TL24: 8.8835380458316097e-09, -8.8835380458316097e-09</I>
   <I>TL25: -4.0295172348123742e-03, 4.0295172348123742e-03</I>
   <I>TL26: 3.8963998704275582e-03, -3.8963998704275582e-03</I>
   <I>TL27: 1.3310848044056911e-04, -1.3310848044056911e-04</I>
   <I>TL28: -2.6914927349269629e-14, 2.6914927349269629e-14</I>
   <I>TL29: -2.9019688182704488e-08, 2.9019688182704488e-08</I>
   <I>TL3: 3.2149451082440658e-17, -3.2149451082440658e-17</I>
   <I>TL30: -1.3209917418862460e-02, 1.3209917418862460e-02</I>
   <I>TL31: -1.3209917415224481e-02, 1.3209917415224481e-02</I>
   <I>TL32: 2.6914927349268013e-14, -2.6914927349268013e-14</I>
   <I>TL33: 3.8963998694901969e-03, -3.8963998694901969e-03</I>
   <I>TL34: 6.6714984390290888e-03, -6.6714984390290888e-03</I>
   <I>TL35: 6.6714984390290888e-03, -6.6714984390290888e-03</I>
   <I>TL36: 2.9019715130917945e-08, -2.9019715130917945e-08</I>
   <I>TL5: 2.9019688183723469e-08, -2.9019688183723469e-08</I>
   <I>TL6: -1.5376697311275667e-16, 1.5376697311275667e-16</I>
   <I>TL7: 8.8835380458577619e-09, -8.8835380458577619e-09</I>
   <I>TL8: 3.8963998686085688e-03, -3.8963998686085688e-03</I>
   <I>TL9: 4.0295172366313636e-03, -4.0295172366313636e-03</I>
   <I>Tee1: -1.5378052563991274e-16, 8.8835381996111825e-09, -8.8835380458306568e-09</I>
   <I>Tee2: 1.7239434651855845e-02, -1.3209917418862460e-02, -4.0295172329933848e-03</I>
   <I>Tee3: -1.3209888400524505e-02, 1.3209917418862460e-02, -2.9020156944170594e-08</I>
   <I>Tee4: 2.9019715130917945e-08, -2.6948929199299698e-14, -2.9019688183723469e-08</I>
   <I>Tee5: 2.6947076800354493e-14, -3.2149451084056245e-17, -2.6914927349270436e-14</I>
   <I>Term1: 1.5377765367276853e-16, -1.5377765367276853e-16</I>
   <I>Term2: 3.2149451083476747e-17, -3.2149451083476747e-17</I>
   <I>Term3: 0.0000000000000000e+00, 0.0000000000000000e+00</I>
   <I>Term4: 0.0000000000000000e+00, 0.0000000000000000e+00</I>
   <I>V1: 3.8963998694902403e-03</I>
   <I>V2: 8.8835380458317586e-09</I>
   <I>V3: 6.6714984390290628e-03</I>
   <I>V4: 6.6714984390290628e-03</I>
   <I>V5: 2.9019688182704147e-08</I>
   <I>V6: 2.6914927349269726e-14</I>
  </DC_PinCurrents>
  <DC_OPInstances/>
 </Controller>
</DCOPData>
